MANIFEST.in
setup.py
src/uritool/__init__.py
src/uritool/__main__.py
src/uritool/urilib.py
src/uritool.egg-info/PKG-INFO
src/uritool.egg-info/SOURCES.txt
src/uritool.egg-info/dependency_links.txt
src/uritool.egg-info/entry_points.txt
src/uritool.egg-info/not-zip-safe
src/uritool.egg-info/requires.txt
src/uritool.egg-info/top_level.txt