Metadata-Version: 1.1
Name: uritool
Version: 0.1.1
Summary: Extract data from the URI Online Judge website at https://www.urionlinejudge.com.br/
Home-page: https://github.com/fabiommendes/uritool/
Author: Fábio Macêdo Mendes
Author-email: fabiomacedomendes@gmail.com
License: GPL
Platform: UNKNOWN
Classifier: Development Status :: 4 - Beta
Classifier: Intended Audience :: Developers
Classifier: License :: OSI Approved :: GNU General Public License (GPL)
Classifier: Operating System :: POSIX
Classifier: Programming Language :: Python
Classifier: Topic :: Software Development :: Libraries
